{
  "queueCards": [
    {
      "name": "Please",
      "description": [ "" ],
      "answer": [ "Se faz favor" ]
    },
    {
      "name": "Sorry",
      "description": [ "" ],
      "answer": [ "Desculpe/a" ]
    },
    {
      "name": "Colours",
      "description": [
        "Red", "Pink", "Orange",
        "Yellow", "Green", "Blue",
        "Violet", "Lilac", "White",
        "Black", "Grey", "Brown"
      ],
      "answer": [
        "Vermelho", "Cor de rosa", "Cor de laranja",
        "Amarelo", "Verde", "Azul",
        "Violeta", "Lilás", "Branco",
        "Preto", "Cinza", "Marrom"
      ]
    },
    {
      "name": "Introduce yourself",
      "description": [ "" ],
      "answer": [
        "Olá!",
        "Chamo-me Owen",
        "Eu seu Canadiano e eu vivo em Montréal",
        "Eu tens vinte e quatro anos"
      ]
    },
    {
      "name": "Numbers",
      "description":  [ "0-10" ],
      "answer": [
        "zero",
        "um", "dois", "três", "quatro", "cinco",
        "seis", "sete", "oito", "nove", "dez"
      ]
    },
    {
      "name": "Seasons",
      "description": [ "" ],
      "answer": [ "Inverno", "Primavera", "Verão", "Outono" ]
    },
    {
      "name": "Positionality",
      "description": [
        "in front of", "behind", "beside",
        "between", "above", "under", "inside"
      ],
      "answer": [
        "em frente de", "atrás de", "ao lado de",
        "entre", "em cima de", "debaixo de", "dentro da"
      ]
    },
    {
      "name": "Tell the current time",
      "description": [ "" ],
      "answer": [
        "[#] (e [meia/quarto/#]) da [manhã/tarde/noite]",
        "[quarto/#] pras [#]",
        "meio-[dia/noite]"
      ]
    },
    {
      "name": "Meals of the day",
      "description": [ "breakfast", "lunch", "dinner" ],
      "answer": [ "pequeno-almoço", "almoço", "jantar" ]
    },
    {
      "name": "Goodbye",
      "description": [ "" ],
      "answer": [ "Ate ja" ]
    },
    {
      "name": "Marital status",
      "description": [
        "Single", "Partnered (Boyfriend/Girlfriend)",
        "Engaged (Fiancé/Fiancée)", "Married (Husband/Wife)",
        "Divorced (Ex-huband/Ex-wife)", "Widower/Widow (dead Husband/Wife)"
      ],
      "answer": [
        "Soltero/a", "Casado/a (Namorado/a)",
        "Casado/a (Noivo/a)", "Casado/a (Marido/Esposa)",
        "Divorciado/a (Ex-Marido/Ex-Esposa)", "Viuvo/a (Falceido/a)"
      ]
    },
    {
      "name": "here / there / there (far)",
      "description": [ "" ],
      "answer": [ "aqui", "ali", "lá" ]
    },
    {
      "name": "Days of the week",
      "description": [ "Starting with Monday" ],
      "answer": [
        "segunda-feira", "terça-feira", "quarta-feira",
        "quinta-feira", "sexta-feira",
        "sábado", "domingo", "fim-da-semana"
      ]
    },
    {
      "name": "Thank you / You're welcome",
      "description": [ "" ],
      "answer": [ "Obrigado/a", "De nada" ]
    },
    {
      "name": "Months",
      "description": [ "" ],
      "answer": [
        "janeiro", "fevereiro", "março",
        "abril", "maio", "junho",
        "julho", "agosto", "setembro",
        "outubro", "novembro", "dezembro"
      ]
    },
    {
      "name": "Numbers",
      "description": [ "11-20" ],
      "answer": [
        "onze", "doze", "treze", "quatorze", "quinze",
        "dezesseis", "dezessete", "dezoito", "dezenove", "vinte"
      ]
    },
    {
      "name": "Family",
      "description": [
        "Father", "Mother",
        "Brother", "Sister", "Siblings",
        "Uncle", "Aunt",
        "Grandfather", "Grandmother", "Grandparents"
      ],
      "answer": [
        "o pai", "a mãe",
        "o irmão", "a irmã", "os irmãos", "as irmãs",
        "o tio", "a tia",
        "o avô", "a avó", "o avós"
      ]
    },
    {
      "name": "Days",
      "description": [ "today", "yesterday", "day before yesterday", "tomorrow" ],
      "answer": [ "hoje", "ontem", "anteontem", "amanhã" ]
    },
    {
      "name": "Fruit",
      "description": [
        "Orange", "Guava", "Grape", "Avocado", "Plum",
        "Pineapple", "Mango", "Papaya", "Lemon", "Strawberry",
        "Coconut", "Pear", "Watermelon", "Melon", "Peach",
        "Passion Fruit", "Apple"
      ],
      "answer": [
        "Laranja", "Goiaba", "Uva", "Abacate", "Ameixa",
        "Abacaxi", "Manga", "Mamão", "Limão", "Marango",
        "Coco", "Pera", "Melancia", "Malão", "Pêssego",
        "Maracujà", "Maçã"
      ]
    },
    {
      "name": "Important verbs",
      "description": [
        "ser", "ter", "chamar", "falar", "morar",
        "trabalhar", "jogar", "gostar", "estudar", "comprar",
        "tomar", "tocar", "pagar", "comer", "beber"
      ],
      "answer": [
        "be", "have", "name / be named", "speak", "reside",
        "work", "play", "like", "study", "buy",
        "take", "touch", "pay", "eat", "drink"
      ]
    },
    {
      "name": "Body parts",
      "description": [
        "head", "hair", "eye", "ear", "nose",
        "mouth", "neck", "shoulder", "arm", "elbow",
        "stomach", "waist", "hand", "fingers", "thigh",
        "hip", "leg", "knee", "foot", "toes",
        "ankle"
      ],
      "answer": [
        "a cabeça", "o cabelo", "o olho", "a orelha", "o nariz",
        "a boca", "o pescoço", "o ombro", "o braço", "o cotovelo",
        "a barriga", "a cintura", "a mão", "os dedos", "a coxa",
        "o quadril", "a perna", "o joelho", "o pé", "os dedos do pé",
        "o tornozelo"
      ]
    }
  ],
  "usefulPhrases": [
    {
      "phrase": "Olá!",
      "answer": "Hello!"
    }
  ],
  "verbs": [
      {
        "name": "ser",
        "past":
        {
          "first": "",
          "second": "",
          "third": "",
          "fourth": "",
          "fifth": "",
          "sixth": ""
        },
        "present":
        {
          "first": "sou",
          "second": "és",
          "third": "é",
          "fourth": "somos",
          "fifth": "sois",
          "sixth": "são"
        },
        "future":
        {
          "first": "",
          "second": "",
          "third": "",
          "fourth": "",
          "fifth": "",
          "sixth": ""
        }
      },
      {
        "name": "ter",
        "past":
        {
          "first": "",
          "second": "",
          "third": "",
          "fourth": "",
          "fifth": "",
          "sixth": ""
        },
        "present":
        {
          "first": "tenho",
          "second": "tens",
          "third": "tem",
          "fourth": "temos",
          "fifth": "tendes",
          "sixth": "têm"
        },
        "future":
        {
          "first": "",
          "second": "",
          "third": "",
          "fourth": "",
          "fifth": "",
          "sixth": ""
        }
      },
      {
        "name": "chamar",
        "past":
        {
          "first": "",
          "second": "",
          "third": "",
          "fourth": "",
          "fifth": "",
          "sixth": ""
        },
        "present":
        {
          "first": "chamo",
          "second": "chamas",
          "third": "chama",
          "fourth": "chamamos",
          "fifth": "chamais",
          "sixth": "chamam"
        },
        "future":
        {
          "first": "",
          "second": "",
          "third": "",
          "fourth": "",
          "fifth": "",
          "sixth": ""
        }
      },
      {
        "name": "falar",
        "past":
        {
          "first": "",
          "second": "",
          "third": "",
          "fourth": "",
          "fifth": "",
          "sixth": ""
        },
        "present":
        {
          "first": "falo",
          "second": "falas",
          "third": "fala",
          "fourth": "falamos",
          "fifth": "falais",
          "sixth": "falem"
        },
        "future":
        {
          "first": "",
          "second": "",
          "third": "",
          "fourth": "",
          "fifth": "",
          "sixth": ""
        }
      },
      {
        "name": "morar",
        "past":
        {
          "first": "",
          "second": "",
          "third": "",
          "fourth": "",
          "fifth": "",
          "sixth": ""
        },
        "present":
        {
          "first": "moro",
          "second": "moras",
          "third": "mora",
          "fourth": "moramos",
          "fifth": "morais",
          "sixth": "moram"
        },
        "future":
        {
          "first": "",
          "second": "",
          "third": "",
          "fourth": "",
          "fifth": "",
          "sixth": ""
        }
      },
      {
        "name": "trabalhar",
        "past":
        {
          "first": "",
          "second": "",
          "third": "",
          "fourth": "",
          "fifth": "",
          "sixth": ""
        },
        "present":
        {
          "first": "trabalho",
          "second": "trabalhas",
          "third": "trabalha",
          "fourth": "trabalhamos",
          "fifth": "trabalhais",
          "sixth": "trabalham"
        },
        "future":
        {
          "first": "",
          "second": "",
          "third": "",
          "fourth": "",
          "fifth": "",
          "sixth": ""
        }
      },
      {
        "name": "jogar",
        "past":
        {
          "first": "",
          "second": "",
          "third": "",
          "fourth": "",
          "fifth": "",
          "sixth": ""
        },
        "present":
        {
          "first": "jogo",
          "second": "jogas",
          "third": "joga",
          "fourth": "jogamos",
          "fifth": "jogais",
          "sixth": "jogam"
        },
        "future":
        {
          "first": "",
          "second": "",
          "third": "",
          "fourth": "",
          "fifth": "",
          "sixth": ""
        }
      },
      {
        "name": "gostar",
        "past":
        {
          "first": "",
          "second": "",
          "third": "",
          "fourth": "",
          "fifth": "",
          "sixth": ""
        },
        "present":
        {
          "first": "gosto",
          "second": "gostas",
          "third": "gosta",
          "fourth": "gostamos",
          "fifth": "gostais",
          "sixth": "gostam"
        },
        "future":
        {
          "first": "",
          "second": "",
          "third": "",
          "fourth": "",
          "fifth": "",
          "sixth": ""
        }
      },
      {
        "name": "estudar",
        "past":
        {
          "first": "",
          "second": "",
          "third": "",
          "fourth": "",
          "fifth": "",
          "sixth": ""
        },
        "present":
        {
          "first": "estudo",
          "second": "estudas",
          "third": "estuda",
          "fourth": "estudamos",
          "fifth": "estudais",
          "sixth": "estudam"
        },
        "future":
        {
          "first": "",
          "second": "",
          "third": "",
          "fourth": "",
          "fifth": "",
          "sixth": ""
        }
      },
      {
        "name": "comprar",
        "past":
        {
          "first": "",
          "second": "",
          "third": "",
          "fourth": "",
          "fifth": "",
          "sixth": ""
        },
        "present":
        {
          "first": "compro",
          "second": "compras",
          "third": "compra",
          "fourth": "compramos",
          "fifth": "comprais",
          "sixth": "compram"
        },
        "future":
        {
          "first": "",
          "second": "",
          "third": "",
          "fourth": "",
          "fifth": "",
          "sixth": ""
        }
      },
      {
        "name": "tomar",
        "past":
        {
          "first": "",
          "second": "",
          "third": "",
          "fourth": "",
          "fifth": "",
          "sixth": ""
        },
        "present":
        {
          "first": "",
          "second": "",
          "third": "",
          "fourth": "",
          "fifth": "",
          "sixth": ""
        },
        "future":
        {
          "first": "",
          "second": "",
          "third": "",
          "fourth": "",
          "fifth": "",
          "sixth": ""
        }
      },
      {
        "name": "tocar",
        "past":
        {
          "first": "",
          "second": "",
          "third": "",
          "fourth": "",
          "fifth": "",
          "sixth": ""
        },
        "present":
        {
          "first": "toco",
          "second": "tocas",
          "third": "toca",
          "fourth": "tocamos",
          "fifth": "tocais",
          "sixth": "tocam"
        },
        "future":
        {
          "first": "",
          "second": "",
          "third": "",
          "fourth": "",
          "fifth": "",
          "sixth": ""
        }
      },
      {
        "name": "pagar",
        "past":
        {
          "first": "",
          "second": "",
          "third": "",
          "fourth": "",
          "fifth": "",
          "sixth": ""
        },
        "present":
        {
          "first": "",
          "second": "",
          "third": "",
          "fourth": "",
          "fifth": "",
          "sixth": ""
        },
        "future":
        {
          "first": "",
          "second": "",
          "third": "",
          "fourth": "",
          "fifth": "",
          "sixth": ""
        }
      },
      {
        "name": "comer",
        "past":
        {
          "first": "",
          "second": "",
          "third": "",
          "fourth": "",
          "fifth": "",
          "sixth": ""
        },
        "present":
        {
          "first": "",
          "second": "",
          "third": "",
          "fourth": "",
          "fifth": "",
          "sixth": ""
        },
        "future":
        {
          "first": "",
          "second": "",
          "third": "",
          "fourth": "",
          "fifth": "",
          "sixth": ""
        }
      },
      {
        "name": "beber",
        "past":
        {
          "first": "",
          "second": "",
          "third": "",
          "fourth": "",
          "fifth": "",
          "sixth": ""
        },
        "present":
        {
          "first": "",
          "second": "",
          "third": "",
          "fourth": "",
          "fifth": "",
          "sixth": ""
        },
        "future":
        {
          "first": "",
          "second": "",
          "third": "",
          "fourth": "",
          "fifth": "",
          "sixth": ""
        }
      }
  ],
  "dictionary": [
    {
      "word": "Olá!",
      "answer": "Hello!"
    }
  ]
}